SDSPy/__init__.py
SDSPy/acquisition/__init__.py
SDSPy/acquisition/acquisition.py
SDSPy/BaseOptionnalClass.py
SDSPy/channel/__init__.py
SDSPy/channel/channel.py
SDSPy/communication/__init__.py
SDSPy/communication/communication.py
SDSPy/cursor/__init__.py
SDSPy/cursor/cursor.py
SDSPy/decode/__init__.py
SDSPy/decode/decode.py
SDSPy/digital/__init__.py
SDSPy/digital/digital.py
SDSPy/digital/digitalchannel.py
SDSPy/display/__init__.py
SDSPy/display/display.py
SDSPy/Files/__init__.py
SDSPy/Files/files.py
SDSPy/generics/__init__.py
SDSPy/generics/generics.py
SDSPy/history/__init__.py
SDSPy/history/history.py
SDSPy/maths/__init__.py
SDSPy/maths/maths.py
SDSPy/measure/__init__.py
SDSPy/measure/measure.py
SDSPy/passfail/__init__.py
SDSPy/passfail/passfail.py
SDSPy/pySDS.py
SDSPy/references/__init__.py
SDSPy/references/references.py
SDSPy/timebase/__init__.py
SDSPy/timebase/timebase.py
SDSPy/trigger/__init__.py
SDSPy/trigger/CAN.py
SDSPy/trigger/IIC.py
SDSPy/trigger/LIN.py
SDSPy/trigger/SPI.py
SDSPy/trigger/trigger.py
SDSPy/trigger/UART.py
SDSPy/waveform/__init__.py
SDSPy/waveform/waveform.py
sdspy-1.1.0.dist-info/LICENSE
sdspy-1.1.0.dist-info/METADATA
sdspy-1.1.0.dist-info/WHEEL
sdspy-1.1.0.dist-info/RECORD
